{
    "version": "0.31.10",
    "architecture": {
        "64bit": {
            "url": "https://github.com/scttfrdmn/spore-host/releases/download/v0.31.10/spawn_0.31.10_windows_amd64.tar.gz",
            "bin": [
                "spawn.exe"
            ],
            "hash": "76b0837c27ee2b5b6f947e64bb4f079a196dd6fb01e4e8cc8c5d1353966d7a57"
        },
        "arm64": {
            "url": "https://github.com/scttfrdmn/spore-host/releases/download/v0.31.10/spawn_0.31.10_windows_arm64.tar.gz",
            "bin": [
                "spawn.exe"
            ],
            "hash": "10a441519f3304cab566747e44946592cce50ca737df502aa2469166b0887f0f"
        }
    },
    "homepage": "https://github.com/scttfrdmn/spore-host",
    "license": "Apache-2.0",
    "description": "Launch ephemeral AWS EC2 instances effortlessly",
    "depends": [
        "scttfrdmn/truffle"
    ]
}
