{
    "version": "0.20.0",
    "architecture": {
        "64bit": {
            "url": "https://github.com/scttfrdmn/mycelium/releases/download/v0.20.0/truffle_0.20.0_windows_amd64.tar.gz",
            "bin": [
                "truffle.exe"
            ],
            "hash": "097414718697d1cfc79726dbe5f53f2daef8554847135c54881cea19073f8f91"
        },
        "arm64": {
            "url": "https://github.com/scttfrdmn/mycelium/releases/download/v0.20.0/truffle_0.20.0_windows_arm64.tar.gz",
            "bin": [
                "truffle.exe"
            ],
            "hash": "4aa1ddc570388c122bf05841c63d753124681a77291885454792a89313276d3a"
        }
    },
    "homepage": "https://github.com/scttfrdmn/mycelium",
    "license": "MIT",
    "description": "Find and discover AWS EC2 instance types"
}
