{
    "version": "0.28.0",
    "architecture": {
        "64bit": {
            "url": "https://github.com/scttfrdmn/spore-host/releases/download/v0.28.0/truffle_0.28.0_windows_amd64.tar.gz",
            "bin": [
                "truffle.exe"
            ],
            "hash": "842f55e0ff5d408d7280a987971dafa2e1b209502db9df3a1194a7a1ba2234f7"
        },
        "arm64": {
            "url": "https://github.com/scttfrdmn/spore-host/releases/download/v0.28.0/truffle_0.28.0_windows_arm64.tar.gz",
            "bin": [
                "truffle.exe"
            ],
            "hash": "320b8260e5b2d723b302a2b04c8e2a3875e29ec1f233cac538556938830e358d"
        }
    },
    "homepage": "https://github.com/scttfrdmn/spore-host",
    "license": "Apache-2.0",
    "description": "Find and discover AWS EC2 instance types"
}
