{
    "version": "0.1.1",
    "architecture": {
        "64bit": {
            "url": "https://github.com/scttfrdmn/mycelium/releases/download/v0.1.1/truffle_0.1.1_windows_amd64.tar.gz",
            "bin": [
                "truffle.exe"
            ],
            "hash": "8e286b190edec0e74d713f974ef6c394969538e672a88bd87e6fff93f37ed703"
        },
        "arm64": {
            "url": "https://github.com/scttfrdmn/mycelium/releases/download/v0.1.1/truffle_0.1.1_windows_arm64.tar.gz",
            "bin": [
                "truffle.exe"
            ],
            "hash": "786836ff7993e45802268a48100dc04093a34ed84b27d25bf22d7cf429d82d4b"
        }
    },
    "homepage": "https://github.com/scttfrdmn/mycelium",
    "license": "MIT",
    "description": "Find and discover AWS EC2 instance types"
}
