{
    "version": "0.7.5",
    "architecture": {
        "64bit": {
            "url": "https://github.com/scttfrdmn/prism/releases/download/v0.7.5/prism_0.7.5_windows_x86_64.zip",
            "bin": [
                "prism.exe",
                "prismd.exe"
            ],
            "hash": "61eee2202082a567c32658a5f681fb5996fee380b2d19a3a36ad663e382f0932"
        },
        "arm64": {
            "url": "https://github.com/scttfrdmn/prism/releases/download/v0.7.5/prism_0.7.5_windows_arm64.zip",
            "bin": [
                "prismd.exe",
                "prism.exe"
            ],
            "hash": "b7f5fec56838a9c792bd539957dcc7f80768ba7c8e8e65c2cfca87c49992e36c"
        }
    },
    "homepage": "https://github.com/scttfrdmn/prism",
    "license": "MIT",
    "description": "CLI tool for launching pre-configured cloud workstations for academic research",
    "post_install": [
        "Write-Host 'Prism installed successfully!'",
        "Write-Host 'Run: prism --help to get started'"
    ]
}
